sismic_viz.py
sismic_viz-0.1.dist-info/DESCRIPTION.rst
sismic_viz-0.1.dist-info/LICENSE.txt
sismic_viz-0.1.dist-info/METADATA
sismic_viz-0.1.dist-info/RECORD
sismic_viz-0.1.dist-info/WHEEL
sismic_viz-0.1.dist-info/metadata.json
sismic_viz-0.1.dist-info/top_level.txt
