Metadata-Version: 2.0
Name: sismic-viz
Version: 0.1
Summary: A simple graphviz visualizer for the python package Sismic
Home-page: https://github.com/drorspei/sismic-viz
Author: Dror Speiser
License: MIT
Platform: UNKNOWN
Classifier: Development Status :: 4 - Beta
Classifier: License :: OSI Approved :: MIT License
Classifier: Programming Language :: Python :: 3
Requires-Python: >=2.7.10
Requires-Dist: sismic
Requires-Dist: flask
Requires-Dist: future
